hl7conv2-0.2.1.dist-info/METADATA
hl7conv2-0.2.1.dist-info/WHEEL
hl7conv2-0.2.1.dist-info/licenses/LICENSE
hl7conv2/__init__.py
hl7conv2/hl7conv2.cp38-win32.pyd
hl7conv2/hl7conv2.pyi
hl7conv2/py.typed
hl7conv2-0.2.1.dist-info/RECORD
