Metadata-Version: 2.4
Name: hl7conv2
Version: 0.2.1
Classifier: Development Status :: 4 - Beta
Classifier: Intended Audience :: Healthcare Industry
Classifier: Intended Audience :: Developers
Classifier: License :: OSI Approved :: MIT License
Classifier: Operating System :: OS Independent
Classifier: Programming Language :: Python :: 3
Classifier: Programming Language :: Python :: 3.8
Classifier: Programming Language :: Python :: 3.9
Classifier: Programming Language :: Python :: 3.10
Classifier: Programming Language :: Python :: 3.11
Classifier: Programming Language :: Python :: 3.12
Classifier: Programming Language :: Rust
Classifier: Programming Language :: Python :: Implementation :: CPython
Classifier: Programming Language :: Python :: Implementation :: PyPy
Classifier: Topic :: Scientific/Engineering :: Medical Science Apps.
Classifier: Topic :: Software Development :: Libraries :: Python Modules
Classifier: Topic :: Text Processing :: Markup
License-File: LICENSE
Summary: A high-performance HL7 to JSON converter written in Rust with Python bindings
Keywords: hl7,healthcare,json,converter,medical,health-level-7
Home-Page: https://github.com/IlyaKalosha/hl7conv2
Author-email: Ilya Kalosha <kalosha.ilya@yandex.com>
Requires-Python: >=3.8
Project-URL: Homepage, https://github.com/IlyaKalosha/hl7conv2
Project-URL: Change Log, https://github.com/IlyaKalosha/hl7conv2/releases
Project-URL: Issues, https://github.com/IlyaKalosha/hl7conv2/issues
